[
    {
        "key": 1460903735465,
        "name": "ccc",
        "text": "ccc"
    },
    {
        "key": 1460903894903,
        "name": "ni",
        "text": "\u4f60\u597d"
    },
    {
        "key": 1460903903793,
        "name": "mark",
        "text": "\u4f60\u597d\u554a"
    },
    {
        "key": 1460903918176,
        "name": "\u9ece\u660e",
        "text": "\u4f60\u4eec\u597d"
    },
    {
        "key": 1460903936388,
        "name": "\u5c0f\u660e",
        "text": "\u5927\u5bb6\u597d"
    },
    {
        "key": 1460909512199,
        "name": "\u5c0f\u674e",
        "text": "\u7684\u75af\u72c2\u51cf\u80a5\u4f60\u662f\u770b\u4f60\u7a7a\u95f4\u53d1\u4f60\u770b\u5c31\u770b\u4f60\u770b\u89c1\u4e86\u770b\u89c1\u770b\u89c1\u4f60\u59b9\u592b\u7684\u90e8\u95e8\u7684"
    }
]